teamanchorhello.py
teamanchorhello-0.0.13.dist-info/LICENSE
teamanchorhello-0.0.13.dist-info/METADATA
teamanchorhello-0.0.13.dist-info/WHEEL
teamanchorhello-0.0.13.dist-info/top_level.txt
teamanchorhello-0.0.13.dist-info/RECORD
