Metadata-Version: 2.1
Name: teamanchorhello
Version: 0.0.13
Summary: teamanchor say hello using Pypi package.
Author: fanis
Classifier: Programming Language :: Python :: 3
Classifier: License :: OSI Approved :: MIT License
Classifier: Operating System :: OS Independent
Requires-Python: >=3.6
License-File: LICENSE
